monteprediction/__init__.py
monteprediction/api.py
monteprediction/calendarutil.py
monteprediction/optionsutil.py
monteprediction/scoring.py
monteprediction/submission.py
monteprediction/truth.py
monteprediction/verification.py
monteprediction-1.0.19.dist-info/LICENSE
monteprediction-1.0.19.dist-info/METADATA
monteprediction-1.0.19.dist-info/WHEEL
monteprediction-1.0.19.dist-info/entry_points.txt
monteprediction-1.0.19.dist-info/top_level.txt
monteprediction-1.0.19.dist-info/RECORD
